abyz/__init__.py
abyz/__main__.py
abyz/compiler.py
abyz/correct.py
abyz/global_constants.py
abyz/replacements.py
abyz/syntax_check.py
abyz/reserved/keywords.json
abyz/reserved/numbers.json
abyz-1.0.0.dist-info/METADATA
abyz-1.0.0.dist-info/WHEEL
abyz-1.0.0.dist-info/entry_points.txt
abyz-1.0.0.dist-info/licenses/LICENSE
abyz-1.0.0.dist-info/RECORD
