Metadata-Version: 2.4
Name: abyz
Version: 1.0.0
Summary: Programming language which only uses alphabetical characters
Author-email: Pablo Villanueva Domingo <pablo.villanueva.domingo@gmail.com>
License-File: LICENSE
Requires-Python: >=3.8
